win32build2/__init__.py
win32build2-0.0.3.dist-info/LICENSE
win32build2-0.0.3.dist-info/METADATA
win32build2-0.0.3.dist-info/WHEEL
win32build2-0.0.3.dist-info/top_level.txt
win32build2-0.0.3.dist-info/RECORD
