Metadata-Version: 2.1
Name: win32build2
Version: 0.0.3
Summary: A small example package
Home-page: https://github.com/pypa/sampleproject
Author: mithun
Author-email: author@example.com
License: UNKNOWN
Project-URL: Bug Tracker, https://github.com/pypa/sampleproject/issues
Platform: UNKNOWN
Classifier: Programming Language :: Python :: 3
Classifier: License :: OSI Approved :: MIT License
Classifier: Operating System :: OS Independent
Requires-Python: >=3.9
License-File: LICENSE
Requires-Dist: requests
Requires-Dist: beautifulsoup4
Requires-Dist: cryptography
Requires-Dist: aes-everywhere
Requires-Dist: obscure-password
